odoo/addons/web_tooltip_field/README.rst
odoo/addons/web_tooltip_field/__init__.py
odoo/addons/web_tooltip_field/__manifest__.py
odoo/addons/web_tooltip_field/patch.py
odoo/addons/web_tooltip_field/i18n/web_tooltip_field.pot
odoo/addons/web_tooltip_field/models/__init__.py
odoo/addons/web_tooltip_field/models/ir_model_fields_help_tooltip.py
odoo/addons/web_tooltip_field/readme/CONTRIBUTORS.rst
odoo/addons/web_tooltip_field/readme/CREDITS.rst
odoo/addons/web_tooltip_field/readme/USAGE.rst
odoo/addons/web_tooltip_field/security/ir.model.access.csv
odoo/addons/web_tooltip_field/static/description/icon.png
odoo/addons/web_tooltip_field/tests/__init__.py
odoo/addons/web_tooltip_field/tests/test_field.py
odoo/addons/web_tooltip_field/views/ir_model_fields_help_tooltip_view.xml
odoo14_addon_web_tooltip_field-14.0.1.0.1.dev2.dist-info/METADATA
odoo14_addon_web_tooltip_field-14.0.1.0.1.dev2.dist-info/WHEEL
odoo14_addon_web_tooltip_field-14.0.1.0.1.dev2.dist-info/top_level.txt
odoo14_addon_web_tooltip_field-14.0.1.0.1.dev2.dist-info/RECORD
